certbot_dns_dreamhost/__init__.py
certbot_dns_dreamhost/dns_dreamhost.py
certbot_dns_dreamhost-1.0.dist-info/LICENSE.md
certbot_dns_dreamhost-1.0.dist-info/METADATA
certbot_dns_dreamhost-1.0.dist-info/WHEEL
certbot_dns_dreamhost-1.0.dist-info/entry_points.txt
certbot_dns_dreamhost-1.0.dist-info/top_level.txt
certbot_dns_dreamhost-1.0.dist-info/RECORD
