Metadata-Version: 2.1
Name: certbot-dns-dreamhost
Version: 1.0
Summary: DreamHost DNS Authenticator plugin for Certbot
Home-page: https://github.com/goncalo-leal/certbot-dns-dreamhost
Author: Gonçalo Leal
Author-email: goncalolealsilva@ua.pt
License: Apache License 2.0
License-File: LICENSE.md
Requires-Dist: acme (>=0.29.0)
Requires-Dist: certbot (>=0.34.0)
Requires-Dist: setuptools
Requires-Dist: requests
